cpf_playground/__init__.py
cpf_playground/formatting.py
cpf_playground/generation.py
cpf_playground/validation.py
cpf_playground-0.0.1.dist-info/METADATA
cpf_playground-0.0.1.dist-info/WHEEL
cpf_playground-0.0.1.dist-info/top_level.txt
cpf_playground-0.0.1.dist-info/RECORD
