Metadata-Version: 2.4
Name: cpf_playground
Version: 0.0.1
Summary: A Brazilian CPF manipulator package
Home-page: https://github.com/bernard-rodrigues/cpf_playground/
Author: bernard_clint
Author-email: bclintwood@gmail.com
Requires-Python: >=3.5
Dynamic: author
Dynamic: author-email
Dynamic: description
Dynamic: description-content-type
Dynamic: home-page
Dynamic: requires-python
Dynamic: summary
